Metadata-Version: 2.1
Name: notfunny
Version: 0.6.15
Summary: Only the worst
Home-page: http://github.com/ohthepain/notfunny
Author: Paul Wilkinson
Author-email: paul@thisco.co
License: MIT
Keywords: joke
Classifier: Development Status :: 3 - Alpha
Classifier: License :: OSI Approved :: MIT License
Classifier: Programming Language :: Python :: 3.8
Classifier: Topic :: Text Processing :: Linguistic
